{
  "openapi": "3.0.1",
  "info": {
    "title": "CinemaApp.WebAPI",
    "version": "1.0"
  },
  "paths": {
    "/api/CinemaMovieApi/Showtimes": {
      "get": {
        "tags": [
          "CinemaMovieApi"
        ],
        "parameters": [
          {
            "name": "cinemaId",
            "in": "query",
            "schema": {
              "type": "string"
            }
          },
          {
            "name": "movieId",
            "in": "query",
            "schema": {
              "type": "string"
            }
          }
        ],
        "responses": {
          "200": {
            "description": "OK",
            "content": {
              "text/plain": {
                "schema": {
                  "type": "array",
                  "items": {
                    "type": "string"
                  }
                }
              },
              "application/json": {
                "schema": {
                  "type": "array",
                  "items": {
                    "type": "string"
                  }
                }
              },
              "text/json": {
                "schema": {
                  "type": "array",
                  "items": {
                    "type": "string"
                  }
                }
              }
            }
          }
        }
      }
    },
    "/api/CinemaMovieApi/AvailableTickets": {
      "get": {
        "tags": [
          "CinemaMovieApi"
        ],
        "parameters": [
          {
            "name": "cinemaId",
            "in": "query",
            "schema": {
              "type": "string"
            }
          },
          {
            "name": "movieId",
            "in": "query",
            "schema": {
              "type": "string"
            }
          },
          {
            "name": "showtime",
            "in": "query",
            "schema": {
              "type": "string"
            }
          }
        ],
        "responses": {
          "200": {
            "description": "OK",
            "content": {
              "text/plain": {
                "schema": {
                  "type": "integer",
                  "format": "int32"
                }
              },
              "application/json": {
                "schema": {
                  "type": "integer",
                  "format": "int32"
                }
              },
              "text/json": {
                "schema": {
                  "type": "integer",
                  "format": "int32"
                }
              }
            }
          }
        }
      }
    },
    "/Home/Error/{statusCode}": {
      "get": {
        "tags": [
          "Home"
        ],
        "parameters": [
          {
            "name": "statusCode",
            "in": "path",
            "required": true,
            "schema": {
              "type": "integer",
              "format": "int32"
            }
          }
        ],
        "responses": {
          "200": {
            "description": "OK"
          }
        }
      }
    },
    "/api/internal/TicketApi/Buy": {
      "post": {
        "tags": [
          "TicketApi"
        ],
        "requestBody": {
          "content": {
            "application/json": {
              "schema": {
                "$ref": "#/components/schemas/BuyRequestModel"
              }
            },
            "text/json": {
              "schema": {
                "$ref": "#/components/schemas/BuyRequestModel"
              }
            },
            "application/*+json": {
              "schema": {
                "$ref": "#/components/schemas/BuyRequestModel"
              }
            }
          }
        },
        "responses": {
          "200": {
            "description": "OK"
          }
        }
      }
    },
    "/WeatherForecast": {
      "get": {
        "tags": [
          "WeatherForecast"
        ],
        "operationId": "GetWeatherForecast",
        "responses": {
          "200": {
            "description": "OK",
            "content": {
              "text/plain": {
                "schema": {
                  "type": "array",
                  "items": {
                    "$ref": "#/components/schemas/WeatherForecast"
                  }
                }
              },
              "application/json": {
                "schema": {
                  "type": "array",
                  "items": {
                    "$ref": "#/components/schemas/WeatherForecast"
                  }
                }
              },
              "text/json": {
                "schema": {
                  "type": "array",
                  "items": {
                    "$ref": "#/components/schemas/WeatherForecast"
                  }
                }
              }
            }
          }
        }
      }
    }
  },
  "components": {
    "schemas": {
      "BuyRequestModel": {
        "required": [
          "cinemaId",
          "movieId",
          "quantity",
          "showtime"
        ],
        "type": "object",
        "properties": {
          "cinemaId": {
            "minLength": 1,
            "type": "string"
          },
          "movieId": {
            "minLength": 1,
            "type": "string"
          },
          "showtime": {
            "minLength": 1,
            "type": "string"
          },
          "quantity": {
            "maximum": 100,
            "minimum": 1,
            "type": "integer",
            "format": "int32"
          }
        },
        "additionalProperties": false
      },
      "WeatherForecast": {
        "type": "object",
        "properties": {
          "date": {
            "type": "string",
            "format": "date"
          },
          "temperatureC": {
            "type": "integer",
            "format": "int32"
          },
          "temperatureF": {
            "type": "integer",
            "format": "int32",
            "readOnly": true
          },
          "summary": {
            "type": "string",
            "nullable": true
          }
        },
        "additionalProperties": false
      }
    }
  }
}